squashy/__init__.py
squashy/agglomeration.py
squashy/decomposition.py
squashy/metrics.py
squashy-0.1.1.dist-info/METADATA
squashy-0.1.1.dist-info/WHEEL
squashy-0.1.1.dist-info/RECORD
