Metadata-Version: 2.1
Name: squashy
Version: 0.1.1
Summary: Large scale graph compression and summarization tool built on Memgraph.
Home-page: https://github.com/Minyall/squashy
Author: James Allen-Robertson
Author-email: minyall@gmail.com
Requires-Python: >=3.10,<4.0
Classifier: Programming Language :: Python :: 3
Classifier: Programming Language :: Python :: 3.10
Classifier: Programming Language :: Python :: 3.11
Requires-Dist: mini-memgraph (>=0.1.0,<0.2.0)
Requires-Dist: pandas (>=2.0.0,<3.0.0)
Requires-Dist: plotly (>=5.14.1,<6.0.0)
Requires-Dist: tqdm (>=4.65.0,<5.0.0)
Project-URL: Repository, https://github.com/Minyall/squashy
